{"data":{"name":"program","content":"","row":1,"col":1,"children":[{"name":"program_head","content":"","row":1,"col":1,"children":[{"name":"PROGRAM","content":"program","row":1,"col":1,"children":[]},{"name":"ID","content":"hello","row":1,"col":8,"children":[]},{"name":"SEMI","content":";","row":1,"col":13,"children":[]}]},{"name":"routine","content":"","row":2,"col":4,"children":[{"name":"routine_head","content":"","row":2,"col":4,"children":[{"name":"undefined","content":"const_part no member","row":2,"col":4,"children":[]},{"name":"undefined","content":"type_part no member","row":2,"col":4,"children":[]},{"name":"var_part","content":"","row":2,"col":1,"children":[{"name":"VAR","content":"var","row":2,"col":1,"children":[]},{"name":"var_decl_list","content":"","row":3,"col":8,"children":[{"name":"var_decl","content":"","row":3,"col":8,"children":[{"name":"name_list","content":"","row":3,"col":8,"children":[{"name":"ID","content":"ans","row":3,"col":8,"children":[]}]},{"name":"COLON","content":":","row":3,"col":11,"children":[]},{"name":"type_decl","content":"","row":3,"col":12,"children":[{"name":"simple_type_decl","content":"","row":3,"col":12,"children":[{"name":"SYS_TYPE","content":"integer","row":3,"col":12,"children":[]}]}]},{"name":"SEMI","content":";","row":3,"col":19,"children":[]}]}]}]},{"name":"routine_part","content":"","row":5,"col":1,"children":[{"name":"function_decl","content":"","row":5,"col":1,"children":[{"name":"function_head","content":"","row":5,"col":1,"children":[{"name":"FUNCTION","content":"function","row":5,"col":1,"children":[]},{"name":"ID","content":"gcd","row":5,"col":9,"children":[]},{"name":"parameters","content":"","row":5,"col":12,"children":[{"name":"LP","content":"(","row":5,"col":12,"children":[]},{"name":"para_decl_list","content":"","row":5,"col":13,"children":[{"name":"para_type_list","content":"","row":5,"col":13,"children":[{"name":"val_para_list","content":"","row":5,"col":13,"children":[{"name":"name_list","content":"","row":5,"col":13,"children":[{"name":"name_list","content":"","row":5,"col":13,"children":[{"name":"ID","content":"a","row":5,"col":13,"children":[]}]},{"name":"COMMA","content":",","row":5,"col":14,"children":[]},{"name":"ID","content":"b","row":5,"col":15,"children":[]}]}]},{"name":"COLON","content":":","row":5,"col":16,"children":[]},{"name":"simple_type_decl","content":"","row":5,"col":17,"children":[{"name":"SYS_TYPE","content":"integer","row":5,"col":17,"children":[]}]}]}]},{"name":"RP","content":")","row":5,"col":24,"children":[]}]},{"name":"COLON","content":":","row":5,"col":25,"children":[]},{"name":"simple_type_decl","content":"","row":5,"col":26,"children":[{"name":"SYS_TYPE","content":"integer","row":5,"col":26,"children":[]}]}]},{"name":"SEMI","content":";","row":5,"col":33,"children":[]},{"name":"sub_routine","content":"","row":6,"col":6,"children":[{"name":"routine_head","content":"","row":6,"col":6,"children":[{"name":"undefined","content":"const_part no member","row":6,"col":6,"children":[]},{"name":"undefined","content":"type_part no member","row":6,"col":6,"children":[]},{"name":"undefined","content":"var_part no member","row":6,"col":6,"children":[]},{"name":"routine_part","content":"routine_part no member","row":6,"col":6,"children":[]}]},{"name":"routine_body","content":"","row":6,"col":1,"children":[{"name":"compound_stmt","content":"","row":6,"col":1,"children":[{"name":"SBEGIN","content":"begin","row":6,"col":1,"children":[]},{"name":"stmt_list","content":"","row":6,"col":6,"children":[{"name":"stmt_list","content":"stmt_list no member","row":6,"col":6,"children":[]},{"name":"stmt","content":"","row":7,"col":8,"children":[{"name":"non_label_stmt","content":"","row":7,"col":8,"children":[{"name":"if_stmt","content":"","row":7,"col":8,"children":[{"name":"IF","content":"if","row":7,"col":8,"children":[]},{"name":"expression","content":"","row":7,"col":10,"children":[{"name":"expression","content":"","row":7,"col":10,"children":[{"name":"expr","content":"","row":7,"col":10,"children":[{"name":"term","content":"","row":7,"col":10,"children":[{"name":"factor","content":"","row":7,"col":10,"children":[{"name":"ID","content":"b","row":7,"col":10,"children":[]}]}]}]}]},{"name":"EQUAL","content":"=","row":7,"col":11,"children":[]},{"name":"expr","content":"","row":7,"col":12,"children":[{"name":"term","content":"","row":7,"col":12,"children":[{"name":"factor","content":"","row":7,"col":12,"children":[{"name":"const_value","content":"","row":7,"col":12,"children":[{"name":"REAL","content":"0","row":7,"col":12,"children":[]}]}]}]}]}]},{"name":"THEN","content":"then","row":7,"col":13,"children":[]},{"name":"stmt","content":"","row":7,"col":17,"children":[{"name":"non_label_stmt","content":"","row":7,"col":17,"children":[{"name":"compound_stmt","content":"","row":7,"col":17,"children":[{"name":"SBEGIN","content":"begin","row":7,"col":17,"children":[]},{"name":"stmt_list","content":"","row":7,"col":22,"children":[{"name":"stmt_list","content":"stmt_list no member","row":7,"col":22,"children":[]},{"name":"stmt","content":"","row":8,"col":16,"children":[{"name":"non_label_stmt","content":"","row":8,"col":16,"children":[{"name":"assign_stmt","content":"","row":8,"col":16,"children":[{"name":"ID","content":"gcd","row":8,"col":16,"children":[]},{"name":"ASSIGN","content":":=","row":8,"col":19,"children":[]},{"name":"expression","content":"","row":8,"col":21,"children":[{"name":"expr","content":"","row":8,"col":21,"children":[{"name":"term","content":"","row":8,"col":21,"children":[{"name":"factor","content":"","row":8,"col":21,"children":[{"name":"ID","content":"a","row":8,"col":21,"children":[]}]}]}]}]}]}]}]},{"name":"SEMI","content":";","row":8,"col":22,"children":[]}]},{"name":"END","content":"end","row":9,"col":8,"children":[]}]}]}]},{"name":"else_clause","content":"","row":10,"col":8,"children":[{"name":"ELSE","content":"else","row":10,"col":8,"children":[]},{"name":"stmt","content":"","row":10,"col":12,"children":[{"name":"non_label_stmt","content":"","row":10,"col":12,"children":[{"name":"compound_stmt","content":"","row":10,"col":12,"children":[{"name":"SBEGIN","content":"begin","row":10,"col":12,"children":[]},{"name":"stmt_list","content":"","row":10,"col":17,"children":[{"name":"stmt_list","content":"stmt_list no member","row":10,"col":17,"children":[]},{"name":"stmt","content":"","row":11,"col":16,"children":[{"name":"non_label_stmt","content":"","row":11,"col":16,"children":[{"name":"assign_stmt","content":"","row":11,"col":16,"children":[{"name":"ID","content":"gcd","row":11,"col":16,"children":[]},{"name":"ASSIGN","content":":=","row":11,"col":19,"children":[]},{"name":"expression","content":"","row":11,"col":21,"children":[{"name":"expr","content":"","row":11,"col":21,"children":[{"name":"term","content":"","row":11,"col":21,"children":[{"name":"factor","content":"","row":11,"col":21,"children":[{"name":"ID","content":"gcd","row":11,"col":21,"children":[]},{"name":"LP","content":"(","row":11,"col":24,"children":[]},{"name":"args_list","content":"","row":11,"col":25,"children":[{"name":"args_list","content":"","row":11,"col":25,"children":[{"name":"expression","content":"","row":11,"col":25,"children":[{"name":"expr","content":"","row":11,"col":25,"children":[{"name":"term","content":"","row":11,"col":25,"children":[{"name":"factor","content":"","row":11,"col":25,"children":[{"name":"ID","content":"b","row":11,"col":25,"children":[]}]}]}]}]}]},{"name":"COMMA","content":",","row":11,"col":26,"children":[]},{"name":"expression","content":"","row":11,"col":27,"children":[{"name":"expr","content":"","row":11,"col":27,"children":[{"name":"term","content":"","row":11,"col":27,"children":[{"name":"term","content":"","row":11,"col":27,"children":[{"name":"factor","content":"","row":11,"col":27,"children":[{"name":"ID","content":"a","row":11,"col":27,"children":[]}]}]},{"name":"MOD","content":"%","row":11,"col":28,"children":[]},{"name":"factor","content":"","row":11,"col":29,"children":[{"name":"ID","content":"b","row":11,"col":29,"children":[]}]}]}]}]}]},{"name":"RP","content":")","row":11,"col":30,"children":[]}]}]}]}]}]}]}]},{"name":"SEMI","content":";","row":11,"col":31,"children":[]}]},{"name":"END","content":"end","row":12,"col":8,"children":[]}]}]}]}]}]}]}]},{"name":"SEMI","content":";","row":13,"col":8,"children":[]}]},{"name":"END","content":"end","row":14,"col":1,"children":[]}]}]}]},{"name":"SEMI","content":";","row":15,"col":1,"children":[]}]}]}]},{"name":"routine_body","content":"","row":17,"col":1,"children":[{"name":"compound_stmt","content":"","row":17,"col":1,"children":[{"name":"SBEGIN","content":"begin","row":17,"col":1,"children":[]},{"name":"stmt_list","content":"","row":17,"col":6,"children":[{"name":"stmt_list","content":"","row":17,"col":6,"children":[{"name":"stmt_list","content":"stmt_list no member","row":17,"col":6,"children":[]},{"name":"stmt","content":"","row":18,"col":8,"children":[{"name":"non_label_stmt","content":"","row":18,"col":8,"children":[{"name":"assign_stmt","content":"","row":18,"col":8,"children":[{"name":"ID","content":"ans","row":18,"col":8,"children":[]},{"name":"ASSIGN","content":":=","row":18,"col":11,"children":[]},{"name":"expression","content":"","row":18,"col":13,"children":[{"name":"expr","content":"","row":18,"col":13,"children":[{"name":"term","content":"","row":18,"col":13,"children":[{"name":"term","content":"","row":18,"col":13,"children":[{"name":"factor","content":"","row":18,"col":13,"children":[{"name":"ID","content":"gcd","row":18,"col":13,"children":[]},{"name":"LP","content":"(","row":18,"col":16,"children":[]},{"name":"args_list","content":"","row":18,"col":17,"children":[{"name":"args_list","content":"","row":18,"col":17,"children":[{"name":"expression","content":"","row":18,"col":17,"children":[{"name":"expr","content":"","row":18,"col":17,"children":[{"name":"term","content":"","row":18,"col":17,"children":[{"name":"factor","content":"","row":18,"col":17,"children":[{"name":"const_value","content":"","row":18,"col":17,"children":[{"name":"REAL","content":"9.1","row":18,"col":17,"children":[]}]}]}]}]}]}]},{"name":"COMMA","content":",","row":18,"col":20,"children":[]},{"name":"expression","content":"","row":18,"col":21,"children":[{"name":"expr","content":"","row":18,"col":21,"children":[{"name":"term","content":"","row":18,"col":21,"children":[{"name":"factor","content":"","row":18,"col":21,"children":[{"name":"const_value","content":"","row":18,"col":21,"children":[{"name":"INTEGER","content":"36","row":18,"col":21,"children":[]}]}]}]}]}]}]},{"name":"RP","content":")","row":18,"col":23,"children":[]}]}]},{"name":"MUL","content":"*","row":18,"col":24,"children":[]},{"name":"factor","content":"","row":18,"col":25,"children":[{"name":"ID","content":"gcd","row":18,"col":25,"children":[]},{"name":"LP","content":"(","row":18,"col":28,"children":[]},{"name":"args_list","content":"","row":18,"col":29,"children":[{"name":"args_list","content":"","row":18,"col":29,"children":[{"name":"expression","content":"","row":18,"col":29,"children":[{"name":"expr","content":"","row":18,"col":29,"children":[{"name":"term","content":"","row":18,"col":29,"children":[{"name":"factor","content":"","row":18,"col":29,"children":[{"name":"const_value","content":"","row":18,"col":29,"children":[{"name":"INTEGER","content":"3","row":18,"col":29,"children":[]}]}]}]}]}]}]},{"name":"COMMA","content":",","row":18,"col":30,"children":[]},{"name":"expression","content":"","row":18,"col":31,"children":[{"name":"expr","content":"","row":18,"col":31,"children":[{"name":"term","content":"","row":18,"col":31,"children":[{"name":"factor","content":"","row":18,"col":31,"children":[{"name":"const_value","content":"","row":18,"col":31,"children":[{"name":"INTEGER","content":"6","row":18,"col":31,"children":[]}]}]}]}]}]}]},{"name":"RP","content":")","row":18,"col":32,"children":[]}]}]}]}]}]}]}]},{"name":"SEMI","content":";","row":18,"col":33,"children":[]}]},{"name":"stmt","content":"","row":19,"col":8,"children":[{"name":"non_label_stmt","content":"","row":19,"col":8,"children":[{"name":"proc_stmt","content":"","row":19,"col":8,"children":[{"name":"SYS_PROC","content":"writeln","row":19,"col":8,"children":[]},{"name":"LP","content":"(","row":19,"col":15,"children":[]},{"name":"expression_list","content":"","row":19,"col":16,"children":[{"name":"expression","content":"","row":19,"col":16,"children":[{"name":"expr","content":"","row":19,"col":16,"children":[{"name":"term","content":"","row":19,"col":16,"children":[{"name":"factor","content":"","row":19,"col":16,"children":[{"name":"ID","content":"ans","row":19,"col":16,"children":[]}]}]}]}]}]},{"name":"RP","content":")","row":19,"col":19,"children":[]}]}]}]},{"name":"SEMI","content":";","row":19,"col":20,"children":[]}]},{"name":"END","content":"end","row":20,"col":1,"children":[]}]}]}]},{"name":"DOT","content":".","row":21,"col":1,"children":[]}]}}